infodump/__init__.py
infodump/command_line.py
infodump/infodump.py
wikidump_infobox_extractor-1.2.0.dist-info/LICENSE
wikidump_infobox_extractor-1.2.0.dist-info/METADATA
wikidump_infobox_extractor-1.2.0.dist-info/WHEEL
wikidump_infobox_extractor-1.2.0.dist-info/entry_points.txt
wikidump_infobox_extractor-1.2.0.dist-info/top_level.txt
wikidump_infobox_extractor-1.2.0.dist-info/RECORD
