Metadata-Version: 2.1
Name: wikidump-infobox-extractor
Version: 1.2.0
Summary: Wikidump infobox extractor.
Home-page: https://github.com/EricWiener/wikidump-infobox-extractor
Author: Eric Wiener
Author-email: ericwiener3@gmail.com
License: UNKNOWN
Platform: UNKNOWN
Classifier: Programming Language :: Python :: 3
Classifier: License :: OSI Approved :: MIT License
Classifier: Operating System :: OS Independent
